sansorchi/__init__.py
sansorchi/__version__.py
sansorchi/data.py
sansorchi/sansorchi.py
Sansorchi-4.0.dist-info/LICENSE
Sansorchi-4.0.dist-info/METADATA
Sansorchi-4.0.dist-info/WHEEL
Sansorchi-4.0.dist-info/top_level.txt
Sansorchi-4.0.dist-info/RECORD
