Metadata-Version: 2.1
Name: Sansorchi
Version: 4.0
Summary: Remove Persian (Farsi) Swear Words
Home-page: https://github.com/KomeilParseh/Sansorchi
Author: KomeilParseh
Author-email: ahmdparsh129@gmail.com
License: UNKNOWN
Download-URL: https://github.com/KomeilParseh/Sansorchi/releases
Keywords: Improper words,swearing,sansorchi,Sansorchi,سانسور,سانسورچی,فحش,پایتون
Platform: UNKNOWN
Classifier: Programming Language :: Python :: 3
Classifier: License :: OSI Approved :: GNU General Public License v3 (GPLv3)
Classifier: Operating System :: OS Independent
Requires-Python: >=3.6
Provides-Extra: dev
Requires-Dist: black ; extra == 'dev'
Requires-Dist: pytest ; extra == 'dev'
Requires-Dist: pylint ; extra == 'dev'
Provides-Extra: docs
Requires-Dist: sphinx ; extra == 'docs'
Requires-Dist: myst-parser ; extra == 'docs'
